multisocks/__init__.py
multisocks/__main__.py
multisocks/bandwidth.py
multisocks/cli.py
multisocks/proxy/__init__.py
multisocks/proxy/proxy_info.py
multisocks/proxy/proxy_manager.py
multisocks/proxy/server.py
multisocks-1.0.6.dist-info/licenses/LICENSE.md
multisocks-1.0.6.dist-info/METADATA
multisocks-1.0.6.dist-info/WHEEL
multisocks-1.0.6.dist-info/entry_points.txt
multisocks-1.0.6.dist-info/top_level.txt
multisocks-1.0.6.dist-info/RECORD
