Metadata-Version: 2.4
Name: multisocks
Version: 1.0.6
Summary: A SOCKS proxy that aggregates multiple remote SOCKS proxies
Author-email: tboy1337 <obywhuie@anonaddy.com>
License: Commercial Restricted License (CRL)
Project-URL: Homepage, https://github.com/tboy1337/multisocks
Project-URL: Bug Tracker, https://github.com/tboy1337/multisocks/issues
Classifier: Programming Language :: Python :: 3
Classifier: Operating System :: OS Independent
Classifier: Development Status :: 4 - Beta
Classifier: Topic :: Internet :: Proxy Servers
Classifier: Topic :: System :: Networking
Requires-Python: >=3.9
License-File: LICENSE.md
Requires-Dist: python-socks
Requires-Dist: aiohttp
Requires-Dist: aiohttp_socks
Requires-Dist: colorama
Dynamic: license-file
